Workbook

Sheet 出口货物报关单
C1: 中华人民共和国海关出口货物报关单
A2: 预录入编号： | G2: 海关编号： | P2: 页码/页数：
A3: 境内发货人 | E3: 出境关别 | G3: 出口日期 | H3: =TEXT(源数据!B1,"yyyy年m月dd日") -> 2024年8月12日 | K3: 申报日期 | L3: =TEXT(源数据!B1,"yyyy年m月dd日") -> 2024年8月12日 | N3: 备案号
A4: 张家港大塚化学有限公司91320592766512130Y | E4: 上海海关 | N4: /
A5: 境外收货人 | E5: 运输方式 | G5: 运输工具名称及航次号 | K5: 提运单号
A6: =源数据!B17 -> OTSUKA CHEMICAL CO LTD | E6: 邮递运输 | K6: =源数据!B5 -> DHL9072950143
A7: 生产销售单位 | E7: 监管方式 | G7: 征免性质 | K7: 许可证号
A8: 张家港大塚化学有限公司91320592766512130Y | E8: 货样广告品A | G8: 一般征税
A9: 合同协议号 | E9: 贸易国(地区) | G9: 运抵国(地区) | K9: 指运港 | N9: 离境口岸
E10: =G10 -> 日本 | G10: =源数据!B6 -> 日本 | K10: =源数据!B6 -> 日本 | N10: 上海浦东
A11: 包装种类 | E11: 件数 | F11: 毛重(千克) | G11: 净重(千克) | I11: 成交方式 | K11: 运费 | M11: 保费 | P11: 杂费
A12: =源数据!B12 -> 纸箱 | E12: =源数据!B8 -> 1 | F12: =源数据!B10 -> 0.8 | G12: =源数据!B9 -> 0.8 | I12: FCA | K12: / | M12: /
A13: 随附单证
A15: 标记唛码及备注
A16: N/M
A17: 项号 | B17: 商品编号 | D17: 商品名称及规格型号 | G17: 数量及单位 | H17: 单价/总价/币制 | K17: 原产国(地区) | L17: 最终目的国(地区) | N17: 境内货源地 | Q17: 征免
A18: 1 | B18: 2841900090 | D18: 钛酸钾（钛拉塞斯）/白色粉末，成分：钛酸钾99%，水分<1%，分子式：K2Ti6O13,CAS NO.12056-51-8 境内收购品牌 享受优惠关税 | G18: =源数据!B9&"千克" -> 0.8千克 | H18: ="5/"&G12*5&"/USD" -> 5/4/USD | K18: 中国 | L18: =源数据!B6 -> 日本 | N18: 张家港其他 | Q18: 照章征税
D42: 特殊关系确认： | E42: 是 | G42: 价格影响确认： | H42: 否 | J42: 支付特许权使用费确认： | M42: 否 | O42: 自报自缴：
A43: 报关人员 | D43: 报关人员证号 | F43: 电话 | H43: 兹申明对以上内容承担如实申报、依法纳税责任 | M43: 海关批注及签章
A45: 申报单位 | J45: 申报单位(签章)

Sheet 报关委托书
A1: 代理报关委托书
A2: 编号：
A3: 我单位现 (A逐票、B长期)委托贵公司代理 等通关事宜。〔A、填单申报 B、申请、联系和配合实施检验检疫 C、辅助查验 D、代缴税款 E、设立手册（账册）F、核销手册（账册）G、领取海关相关单证 H、其他〕详见《委托报关协议》
A4: 我单位保证遵守海关有关法律、法规、规章，保证所提供的情况真实、完整、单货相符，无侵犯他人知识产权的行为。否则，愿承担相关法律责任。
A5: 本委托书有效期自签字之日起至 年 月 日止。
A7: 委托方（盖章）
A8: 法定代表人或其授权签署《代理报关委托书》的人（签字）
A9: 年 月 日
A10: 委托报关协议
A11: 为明确委托报关具体事项和各自责任，双方经平等协商签定协议如下：
A12: 委托方 | B12: =源数据!B2 -> 张家港大塚化学有限公司 | E12: 被委托方
A13: 主要货物名称 | B13: =源数据!B3 -> 钛酸钾（钛拉塞斯） | E13: *报关单编码 | F13: No.
A14: HS编码 | B14: =源数据!B4 -> 2841900090 | E14: 收到单证日期
A15: 进/出口日期 | B15: =TEXT(源数据!B1,"yyyy年m月dd日") -> 2024年8月12日 | E15: 收到单证情况 | F15: 合同□ | G15: 发票□
A16: 提（运）单号 | B16: =源数据!B5 -> DHL9072950143 | F16: 装箱清单□ | G16: 提(运)单□
A17: 贸易方式 | B17: =源数据!B7 -> FCA | F17: 加工贸易手册□ | G17: 许可证件□
A18: 数（重）量 | B18: =源数据!B10&"千克" -> 0.8千克 | F18: 其他
A19: 包装情况 | B19: =源数据!B12 -> 纸箱
A20: 原产地/货源地 | B20: =源数据!B13 -> 张家港
E21: 报关收费 | F21: 人民币： 元
A22: 其他要求： | E22: 承诺说明：
A23: 背面所列通用条款是本协议不可分割的一部分，对本协议的签署构成了对背面通用条款的同意。 | E23: 背面所列通用条款是本协议不可分割的一部分，对本协议的签署构成了对背面通用条款的同意。
A24: 委托方签章： | E24: 被委托方签章：
A26: 经办人签字： | E26: 报关人员签名：
A27: 联系电话： | E27: 联系电话：
A28: 中国报关协会监制
A29: 委托报关协议通用条款
A30: 委托方责任
A31: 委托方应及时提供报关所须的全部单证，并对单证的真实性、准确性和完整性负责，并保证没有侵犯他人知识产权的行为。
A32: 委托方负责在报关企业办结海关手续后，及时、履约支付代理报关费用，支付垫支费用，以及因委托方责任产生的滞报金、滞纳金和海关等执法单位依法处以的各种罚款。
A33: 负责按照海关要求将货物运抵指定场所。
A34: 负责与被委托方报关人员一同协助海关进行查验，回答海关的询问，配合相关调查，并承担产生的相关费用。
A35: 在被委托方无法做到报关前提取货样的情况下，承担单货相符的责任。
A36: 被委托方责任
A37: 负责解答委托方有关向海关申报的疑问。
A38: 负责对委托方提供的货物情况和单证的真实性、完整性进行“合理审查”，审查内容包括：（一）证明进出口货物实际情况的资料，包括进出口货物的品名、规格、数（重）量、包装情况、用途、产地、贸易方式等；（二）有关进出口货物的合同、发票、运输单据、装箱单等商业单据；（三）进出口所需的许可证件及随附单证；（四）海关要求的加工贸易（纸质或电子数据的）及其其他进出口单证。
A39: 因确定货物的品名、归类等原因，经海关批准，可以看货或提取货样。
... A47: 协商解决事项变更、中止本协议或双方发生争议时，按照《中华人民共和国合同法》有关规定及程序处理。因签约双方以外的原因产生的问题或报关业务需要修改协议条款，应协商订立补充协议。双方可以在法律、法规、规章准许的范围内另行签署补充条款，但补充条款不得与本协议的内容相抵触。

Sheet 装箱单
C3: Zhangjiagang Otsuka Chemical Co., Ltd.
A5: Sender: | F5: Packing List
A6: Zhangjiagang Otsuka Chemical Co., Ltd.
A7: =源数据!B14 -> guxiaojuan
A8: Nanhai Road,Yangtze River International Chemical
A9: Industrial Park Zhangjiagang City, Jiangsu Province
A10: Zhangjiagang | C10: 215635
A11: China
A12: Phone:86-512-56907600 | D12: Fax:86-512-56907616
A13: Receiver: | F13: Date: | H13: =TEXT(源数据!B1,"yyyy-m-dd") -> 2024-8-12
A14: Otsuka Chemical Co., Ltd.
A15: Mr.Hamauzu Takashi | F15: Invoice Number:
A17: 463 Kagasuno,Kawauchi-cho | F17: Shipment Reference:
A18: Tokushima 771-0193,Japan
F19: Comments:
A20: PC:771-0193
F21: Air Waybill Number: | H21: =源数据!B5 -> DHL9072950143
A22: TEL:+81-88-665-5909 | C22: FAX:+81-88-665-1540
A29: Full Description of Goods | D29: QTY | E29: commodity | F29: Net Weight(kg) | G29: Gross Weight(KG) | H29: country of maufacture
A30: POTASSIUM TITANIUM OXIDE(TERRACESS) | D30: =源数据!B9&"kg" -> 0.8kg | F30: =源数据!B9 -> 0.8 | G30: =源数据!B10 -> 0.8 | H30: CHINA
D37: Total : | F37: =F30 -> 0.8 | G37: =G30 -> 0.8
A38: Payer of Gst/VAT | D38: ="Total pieces:"&源数据!B8 -> Total pieces:1
A39: Harm.Comm.Code:
A40: Type of Export: | D40: Terms of Trade:
A41: Terms of Payment:
A42: Reason For Export:
A47: I/we hereby certify that the information of this invoice is true n correct n that the contents of this shipment are as stated above
A51: Signature:
A52: position in company:
A53: Shipping Consultant | D53: company Stamp:

Sheet 货物运输安全保证函2份
A1: 货物运输安全保证函 Cargo Safety Transportation Guarantee
A2: 发件公司shipper | B2: Zhangjiagang otsukc chemical co ltd
A3: 生产厂家Manufacturer | B3: Zhangjiagang otsukc chemical co ltd
A4: 运单号 Air Waybill NO. | B4: =源数据!B5 -> DHL9072950143
A5: 货物品名（中文） Shipments Details（Chinese） | B5: 钛酸钾
A6: 货物品名（英文） Shipments Details（English） | B6: POTASSIUM TITANIUM OXIDE（TERRACESS）
A7: 货物运输条件鉴定书编号： Certification No. For Safe Transportation of Chemical Goods | B7: 202400915871422 | F7: 签发日期： Valid Date | G7: 20231221
A8: 鉴定结果 Transportation Information | B8: 普通货物
A9: 包装Packaging | B9: =源数据!B12 -> 纸箱
A10: 始发地/地址Origin Address | B10: 张家港扬子江国际化学工业园南海路
A11: 目的地/地址Destination Address | B11: =源数据!B6 -> 日本
A12: 我公司委托 DHL 承运的该类货物，无爆炸、无氧化、无腐蚀、无放射性、非易燃、非有毒有害、非用于制造化学武器的原料，经 上海化工研究院检测中心 鉴定，无危险性，可按普通货物条件运输，包装符合要求。 The shipment that I consign by DHL does not contain the explosive, oxidation, corrosives, radioactive, flammable, toxic and infectious substance and the material for the chemical weapon. After shanghai research institute of chemical industry testing centre testing, the shipment without fatalness can be transported as the general cargo and the packaging meets the transportation requirement.
A13: 我公司以上申报属实，若由于我公司申报不符，而造成运输过程中的一切损伤，我公司承担一切法律责任和经济赔偿。 I guarantee the truth of above information, or I will take full responsibilities for the result caused by the fake declared information.
A14: 送样单位（公章） Shipper(Stamp) | C14: 生产单位（公章） Manufacturer(Stamp)
A15: 注：1、上述表格务必字迹端正，认真填写。 1、Please carefully and properly fill the blank. 2、如有争议，以中文申明为准！ 2、if disputation occurs, the criterion bases on the Chinese guarantee.

Sheet 发票2份
C3: Zhangjiagang Otsuka Chemical Co., Ltd.
A5: Sender: | F5: Invoice
A6: Zhangjiagang Otsuka Chemical Co., Ltd.
A7: =源数据!B14 -> guxiaojuan
A8: Nanhai Road,Yangtze River International Chemical
A9: Industrial Park Zhangjiagang City, Jiangsu Province
A10: Zhangjiagang | C10: 215635
A11: China
A12: Phone:86-512-56907600 | D12: Fax:86-512-56907616
A13: Receiver: | F13: Date: | G13: =源数据!B1 -> 45516.621
A14: OTSUKA CHEMICAL CO., LTD.
A15: =源数据!B16 -> Mr. OGAWA TAKASHI | F15: Invoice Number:
A16: 463,KAGASUNO KAWAUCHI-CHO,TOKUSHIMA
F17: Shipment Reference:
A19: PC:771-0193 | F19: Comments: | H19: =源数据!B5 -> DHL9072950143
A21: TEL:0081-88-665-5909 | D21: FAX:0081-88-665-1540 | F21: Air Waybill Number:
A23: Bill to Third party
A29: Full Description of Goods | D29: QTY | E29: commodity | F29: Unit Value | G29: Subtotal value | H29: country of maufacture
B30: TERRACESS | D30: =源数据!B9&"kg" -> 0.8kg | F30: ="$"&源数据!B15 -> $5 | G30: ="$"&源数据!B11 -> $4 | H30: CHINA
D41: Total Declared Value: | F41: ="$"&源数据!B11 -> $4
A42: Payer of Gst/VAT | D42: Total pieces: 1 | E42: =源数据!B8 -> 1
A43: Harm.Comm.Code: | E43: Currency Code: ＵＳＤ
A44: Type of Export: | D44: Terms of Trade:
A45: Terms of Payment:
A46: Reason For Export:
A51: I/we hereby certify that the information of this invoice is true and correct and that the contents of this shipment are as stated above
A55: Signature:
A56: position in company:
A57: Shipping Consultant | D57: company Stamp:

Sheet 唛头1份
A2: 中文品名： | B2: =源数据!B3 -> 钛酸钾（钛拉塞斯）
A3: 英文品名： | B3: POTASSIUM TITANIUM OXIDE (TERRACESS)
A4: 生产单位： | B4: =源数据!B2 -> 张家港大塚化学有限公司
A5: 生产单位英文： | B5: ZHANGJIAGANG OTSUKA CHEMICAL CO.,LTD.
A6: 用途： | B6: 主要用作汽车刹车片的添加材料
A7: 物理性状： | B7: 白色粉沫
A8: 运单号 | B8: =源数据!B5 -> DHL9072950143

Sheet 源数据
A1: 日期 | B1: =NOW() -> 45516.621 | C1: 自动获取
A2: 委托方 | B2: 张家港大塚化学有限公司
A3: 主要货物名称 | B3: 钛酸钾（钛拉塞斯）
A4: HS编码 | B4: 2841900090
A5: 提运单号 | B5: DHL9072950143
A6: 最终目的国(地区) | B6: 日本
A7: 贸易方式 | B7: FCA
A8: 数量 | B8: 1
A9: 净重 | B9: 0.8
A10: 毛重 | B10: 0.8
A11: 总价 | B11: =B9*B15 -> 4
A12: 包装类型 | B12: 纸箱
A13: 原产地/货源地 | B13: 张家港
A14: 寄件人 | B14: guxiaojuan
A15: 单价 | B15: 5
A16: 收件人 | B16: Mr. OGAWA TAKASHI
A17: 境外收货人 | B17: OTSUKA CHEMICAL CO LTD
